mapcas/MapsCasApi.py
mapcas/MapsGenericApi.py
mapcas/__init__.py
mapscas-0.1.5.data/data/Scripts/MapsClientParser.dfa
mapscas-0.1.5.data/data/Scripts/MapsClientParser.llr
mapscas-0.1.5.dist-info/DESCRIPTION.rst
mapscas-0.1.5.dist-info/METADATA
mapscas-0.1.5.dist-info/RECORD
mapscas-0.1.5.dist-info/WHEEL
mapscas-0.1.5.dist-info/metadata.json
mapscas-0.1.5.dist-info/top_level.txt
