Metadata-Version: 2.0
Name: mapscas
Version: 0.1.5
Summary: MAPS CAS API Package
Home-page: https://github.com/wtjch/mapscas
Author: Wesley Jinks
Author-email: c-wesley.jinks@charter.com
License: Proprietary
Platform: UNKNOWN
